ecodev_core/__init__.py
ecodev_core/app_activity.py
ecodev_core/app_rights.py
ecodev_core/app_user.py
ecodev_core/auth_configuration.py
ecodev_core/authentication.py
ecodev_core/backup.py
ecodev_core/check_dependencies.py
ecodev_core/custom_equal.py
ecodev_core/db_connection.py
ecodev_core/db_filters.py
ecodev_core/db_i18n.py
ecodev_core/db_insertion.py
ecodev_core/db_retrieval.py
ecodev_core/db_upsertion.py
ecodev_core/deployment.py
ecodev_core/email_sender.py
ecodev_core/encryption.py
ecodev_core/enum_utils.py
ecodev_core/es_connection.py
ecodev_core/list_utils.py
ecodev_core/logger.py
ecodev_core/pandas_utils.py
ecodev_core/permissions.py
ecodev_core/pydantic_utils.py
ecodev_core/read_write.py
ecodev_core/rest_api_client.py
ecodev_core/safe_utils.py
ecodev_core/settings.py
ecodev_core/sqlmodel_utils.py
ecodev_core/token_banlist.py
ecodev_core/version.py
ecodev_core-0.0.81.dist-info/LICENSE.md
ecodev_core-0.0.81.dist-info/METADATA
ecodev_core-0.0.81.dist-info/WHEEL
ecodev_core-0.0.81.dist-info/RECORD
