Metadata-Version: 2.1
Name: ecodev-core
Version: 0.0.81
Summary: Low level sqlmodel/fastapi/pydantic building blocks
License: MIT
Author: Thomas Epelbaum
Author-email: tomepel@gmail.com
Requires-Python: >=3.11,<4.0
Classifier: Development Status :: 2 - Pre-Alpha
Classifier: Environment :: Web Environment
Classifier: Framework :: AsyncIO
Classifier: Framework :: FastAPI
Classifier: Framework :: Pydantic
Classifier: Intended Audience :: Developers
Classifier: Intended Audience :: Information Technology
Classifier: Intended Audience :: Science/Research
Classifier: Intended Audience :: System Administrators
Classifier: License :: OSI Approved :: MIT License
Classifier: Operating System :: OS Independent
Classifier: Programming Language :: Python
Classifier: Programming Language :: Python :: 3
Classifier: Programming Language :: Python :: 3.11
Classifier: Programming Language :: Python :: 3.12
Classifier: Programming Language :: Python :: 3 :: Only
Classifier: Programming Language :: Python :: 3.13
Classifier: Topic :: Database
Classifier: Topic :: Database :: Database Engines/Servers
Classifier: Topic :: Internet
Classifier: Topic :: Internet :: WWW/HTTP
Classifier: Topic :: Internet :: WWW/HTTP :: HTTP Servers
Classifier: Topic :: Software Development
Classifier: Topic :: Software Development :: Libraries
Classifier: Topic :: Software Development :: Libraries :: Application Frameworks
Classifier: Topic :: Software Development :: Libraries :: Python Modules
Classifier: Typing :: Typed
Requires-Dist: asgiref (>=3,<4)
Requires-Dist: bcrypt (>=4,<5)
Requires-Dist: cryptography (>=46,<47)
Requires-Dist: elasticsearch (==8.14.0)
Requires-Dist: fastapi (>=0,<1)
Requires-Dist: httpx (>=0,<1)
Requires-Dist: numpy (>=1,<2)
Requires-Dist: openpyxl (>=3,<4)
Requires-Dist: orjson (>=3,<4)
Requires-Dist: pandas (>=2,<3)
Requires-Dist: passlib (>=1,<2)
Requires-Dist: progressbar2 (>=4,<5)
Requires-Dist: psycopg2-binary (>=2,<3)
Requires-Dist: pydantic (>=2,<3)
Requires-Dist: pydantic-settings (>=2,<3)
Requires-Dist: python-jose (>=3,<4)
Requires-Dist: pyyaml (>=6,<7)
Requires-Dist: requests (>=2,<3)
Requires-Dist: sqladmin (==0.15.2)
Requires-Dist: sqlmodel (>=0,<1)
Requires-Dist: uvicorn (>=0,<1)
Requires-Dist: xlsxwriter (>=3,<4)
